pydantic_stack_core/__init__.py
pydantic_stack_core/__main__.py
pydantic_stack_core/core.py
pydantic_stack_core/fractal.py
pydantic_stack_core/mcp_server.py
pydantic_stack_core-0.1.4.dist-info/METADATA
pydantic_stack_core-0.1.4.dist-info/WHEEL
pydantic_stack_core-0.1.4.dist-info/entry_points.txt
pydantic_stack_core-0.1.4.dist-info/RECORD
