Metadata-Version: 2.4
Name: pydantic-stack-core
Version: 0.1.4
Summary: Minimal library for stackable, renderable Pydantic models
Author: HEAVEN Team
Requires-Python: >=3.9
Requires-Dist: fastmcp>=0.1.0
Requires-Dist: pydantic>=2.0.0
Provides-Extra: dev
Requires-Dist: black>=23.0.0; extra == 'dev'
Requires-Dist: pytest>=7.0.0; extra == 'dev'
Requires-Dist: ruff>=0.1.0; extra == 'dev'
Provides-Extra: registry
Requires-Dist: heaven-framework>=0.1.0; extra == 'registry'
